stable_trunc_gaussian/__init__.py
stable_trunc_gaussian/parallel_trunc_gaussian.py
stable_trunc_gaussian/sequential_trunc_gaussian.py
stable_trunc_gaussian/test_icdf.py
stable_trunc_gaussian/test_kl.py
stable_trunc_gaussian/tests.py
stable_trunc_gaussian-1.3.9.dist-info/LICENSE
stable_trunc_gaussian-1.3.9.dist-info/METADATA
stable_trunc_gaussian-1.3.9.dist-info/WHEEL
stable_trunc_gaussian-1.3.9.dist-info/top_level.txt
stable_trunc_gaussian-1.3.9.dist-info/RECORD
