Metadata-Version: 2.1
Name: stable-trunc-gaussian
Version: 1.3.9
Summary: A numerically-stable and differentiable implementation of the Truncated Gaussian distribution in Pytorch.
Author-email: Carlos Núñez Molina <ccaarlos@ugr.es>
License: MIT License
Project-URL: Homepage, https://github.com/TheAeryan/stable-truncated-gaussian
Keywords: machine-learning,statistics,pytorch,stability
Classifier: License :: OSI Approved :: MIT License
Classifier: Programming Language :: Python
Classifier: Programming Language :: Python :: 3
License-File: LICENSE
Requires-Dist: torch
Provides-Extra: test
Requires-Dist: scipy ; extra == 'test'
